odoo/addons/l10n_es_aeat_sii_invoice_summary/README.rst
odoo/addons/l10n_es_aeat_sii_invoice_summary/__init__.py
odoo/addons/l10n_es_aeat_sii_invoice_summary/__manifest__.py
odoo/addons/l10n_es_aeat_sii_invoice_summary/i18n/es.po
odoo/addons/l10n_es_aeat_sii_invoice_summary/i18n/l10n_es_aeat_sii_invoice_summary.pot
odoo/addons/l10n_es_aeat_sii_invoice_summary/models/__init__.py
odoo/addons/l10n_es_aeat_sii_invoice_summary/models/account_move.py
odoo/addons/l10n_es_aeat_sii_invoice_summary/readme/CONTRIBUTORS.rst
odoo/addons/l10n_es_aeat_sii_invoice_summary/readme/DESCRIPTION.rst
odoo/addons/l10n_es_aeat_sii_invoice_summary/readme/ROADMAP.rst
odoo/addons/l10n_es_aeat_sii_invoice_summary/readme/USAGE.rst
odoo/addons/l10n_es_aeat_sii_invoice_summary/static/description/icon.png
odoo/addons/l10n_es_aeat_sii_invoice_summary/static/description/index.html
odoo/addons/l10n_es_aeat_sii_invoice_summary/tests/__init__.py
odoo/addons/l10n_es_aeat_sii_invoice_summary/tests/test_l10n_es_aeat_sii_invoice_summary.py
odoo/addons/l10n_es_aeat_sii_invoice_summary/tests/json/sii_out_invoice_s_iva0_sp_i_s_iva0_ic_dict.json
odoo/addons/l10n_es_aeat_sii_invoice_summary/tests/json/sii_out_invoice_s_iva0_sp_i_s_iva0_ic_same_dict.json
odoo/addons/l10n_es_aeat_sii_invoice_summary/tests/json/sii_out_invoice_s_iva10b_dict.json
odoo/addons/l10n_es_aeat_sii_invoice_summary/tests/json/sii_out_invoice_s_iva10b_s_irpf1_dict.json
odoo/addons/l10n_es_aeat_sii_invoice_summary/tests/json/sii_out_invoice_s_iva10b_s_irpf1_same_dict.json
odoo/addons/l10n_es_aeat_sii_invoice_summary/tests/json/sii_out_invoice_s_iva10b_s_iva0_ns_dict.json
odoo/addons/l10n_es_aeat_sii_invoice_summary/tests/json/sii_out_invoice_s_iva10b_s_iva0_ns_same_dict.json
odoo/addons/l10n_es_aeat_sii_invoice_summary/tests/json/sii_out_invoice_s_iva10b_s_iva21s_dict.json
odoo/addons/l10n_es_aeat_sii_invoice_summary/tests/json/sii_out_invoice_s_iva10b_s_iva21s_same_dict.json
odoo14_addon_l10n_es_aeat_sii_invoice_summary-14.0.1.3.0.dist-info/METADATA
odoo14_addon_l10n_es_aeat_sii_invoice_summary-14.0.1.3.0.dist-info/WHEEL
odoo14_addon_l10n_es_aeat_sii_invoice_summary-14.0.1.3.0.dist-info/top_level.txt
odoo14_addon_l10n_es_aeat_sii_invoice_summary-14.0.1.3.0.dist-info/RECORD
